steenroder/__init__.py
steenroder/_version.py
steenroder/core.py
steenroder/plotting.py
steenroder/preprocessing.py
steenroder/tests/__init__.py
steenroder/tests/test_core.py
steenroder-0.1.0.dist-info/LICENSE
steenroder-0.1.0.dist-info/METADATA
steenroder-0.1.0.dist-info/WHEEL
steenroder-0.1.0.dist-info/top_level.txt
steenroder-0.1.0.dist-info/RECORD
