Metadata-Version: 2.1
Name: steenroder
Version: 0.1.0
Summary: Computation of persistence Steenrod barcodes 
Home-page: https://github.com/Steenroder/steenroder
Download-URL: https://github.com/Steenroder/steenroder/tarball/v0.1.0
Maintainer: Anibal Medina Mardones, Umberto Lupo
Maintainer-email: steenroder@gmail.com
License: MIT
Keywords: topological data analysis,persistent homology,persistence steenrod modules,persistence steenrod barcodes
Classifier: Intended Audience :: Science/Research
Classifier: Intended Audience :: Developers
Classifier: License :: OSI Approved
Classifier: Programming Language :: Python
Classifier: Topic :: Software Development
Classifier: Topic :: Scientific/Engineering
Classifier: Operating System :: Microsoft :: Windows
Classifier: Operating System :: POSIX
Classifier: Operating System :: Unix
Classifier: Operating System :: MacOS
Classifier: Programming Language :: Python :: 3.8
Classifier: Programming Language :: Python :: 3.9
Classifier: Programming Language :: Python :: 3.10
License-File: LICENSE
Requires-Dist: numpy (>=1.20.3)
Requires-Dist: numba (>=0.53.0)
Requires-Dist: psutil (>=5.8.0)
Requires-Dist: gudhi (>=3.5.0)
Requires-Dist: plotly (>=5.3.1)
Provides-Extra: docs
Requires-Dist: sphinx (>=4.5.0) ; extra == 'docs'
Requires-Dist: jinja2 (==3.0.0) ; extra == 'docs'
Requires-Dist: nbsphinx ; extra == 'docs'
Requires-Dist: sphinx-rtd-theme ; extra == 'docs'
Requires-Dist: ipykernel ; extra == 'docs'
Provides-Extra: tests
Requires-Dist: pytest ; extra == 'tests'
Requires-Dist: pytest-xdist ; extra == 'tests'
Requires-Dist: nbmake ; extra == 'tests'
Requires-Dist: pytest-cov ; extra == 'tests'
Requires-Dist: flake8 ; extra == 'tests'
